sccastle/__init__.py
sccastle/data.py
sccastle/feature_spectrum.py
sccastle/logger.py
sccastle/main.py
sccastle/metrics.py
sccastle/model/__init__.py
sccastle/model/castle_train.py
sccastle/model/layer.py
sccastle/model/utils.py
sccastle-1.0.2.data/scripts/CASTLE.py
sccastle-1.0.2.dist-info/LICENSE
sccastle-1.0.2.dist-info/METADATA
sccastle-1.0.2.dist-info/WHEEL
sccastle-1.0.2.dist-info/top_level.txt
sccastle-1.0.2.dist-info/RECORD
